CHANGELOG.txt
LICENSE.txt
MANIFEST.in
README.txt
setup.py
FormatFuncs/__init__.py
FormatFuncs.egg-info/PKG-INFO
FormatFuncs.egg-info/SOURCES.txt
FormatFuncs.egg-info/dependency_links.txt
FormatFuncs.egg-info/top_level.txt