Metadata-Version: 2.1
Name: FormatFuncs
Version: 0.0.3
Summary: Functions to format strings
Home-page: 
Author: William Rivera - Captain William
Author-email: william.r.2048@gmail.com
License: MIT
Keywords: string,format,paragraph,line break
Classifier: Development Status :: 5 - Production/Stable
Classifier: Intended Audience :: Education
Classifier: Operating System :: Microsoft :: Windows :: Windows 10
Classifier: License :: OSI Approved :: MIT License
Classifier: Programming Language :: Python :: 3
License-File: LICENSE.txt
